MANIFEST.in
README.md
requirements.txt
setup.py
bigcommerce/__init__.py
bigcommerce/api.py
bigcommerce/connection.py
bigcommerce/exception.py
bigcommerce/resources/__init__.py
bigcommerce/resources/base.py
bigcommerce/resources/brands.py
bigcommerce/resources/categories.py
bigcommerce/resources/countries.py
bigcommerce/resources/coupons.py
bigcommerce/resources/customer_groups.py
bigcommerce/resources/customers.py
bigcommerce/resources/option_sets.py
bigcommerce/resources/options.py
bigcommerce/resources/order_statuses.py
bigcommerce/resources/orders.py
bigcommerce/resources/payments.py
bigcommerce/resources/products.py
bigcommerce/resources/redirects.py
bigcommerce/resources/shipping.py
bigcommerce/resources/store.py
bigcommerce/resources/tax_classes.py
bigcommerce/resources/time.py
bigcommerce_api.egg-info/PKG-INFO
bigcommerce_api.egg-info/SOURCES.txt
bigcommerce_api.egg-info/dependency_links.txt
bigcommerce_api.egg-info/requires.txt
bigcommerce_api.egg-info/top_level.txt
tests/__init__.py
tests/test_api.py