Metadata-Version: 1.1
Name: bigcommerce-api
Version: 0.10.1
Summary: Connect Python applications with the Bigcommerce API
Home-page: https://github.com/bigcommerce/bigcommerce-api-python/tree/alpha
Author: Bigcommerce Engineering
Author-email: vip@bigcommerce.com
License: MIT
Keywords: bigcommerce api client
Platform: UNKNOWN
Classifier: Development Status :: 3 - Alpha
Classifier: Topic :: Software Development :: Libraries :: Python Modules
Classifier: Topic :: Office/Business
Classifier: License :: OSI Approved :: MIT License
Classifier: Programming Language :: Python
Classifier: Programming Language :: Python :: 3
